disambiguate.py
leukgen_disambiguate-1.0.1.dist-info/DESCRIPTION.rst
leukgen_disambiguate-1.0.1.dist-info/METADATA
leukgen_disambiguate-1.0.1.dist-info/RECORD
leukgen_disambiguate-1.0.1.dist-info/WHEEL
leukgen_disambiguate-1.0.1.dist-info/entry_points.txt
leukgen_disambiguate-1.0.1.dist-info/metadata.json
leukgen_disambiguate-1.0.1.dist-info/top_level.txt
