Metadata-Version: 2.0
Name: leukgen-disambiguate
Version: 1.0.1
Summary: Disambiguate reads mapping to multiple genomes. This is a frozen release with some bug fixes of the original AstraZeneca-NGS/disambiguate v1.0.
Home-page: UNKNOWN
Author: Miika Ahdesmaki
License: MIT
Platform: UNKNOWN
Classifier: Intended Audience :: Developers
Classifier: Intended Audience :: Science/Research
Classifier: License :: OSI Approved :: MIT License
Classifier: Natural Language :: English
Classifier: Operating System :: Unix
Classifier: Operating System :: POSIX
Classifier: Programming Language :: Python :: 2.7
Classifier: Programming Language :: Python :: 3.6
Classifier: Topic :: Utilities
Provides-Extra: test
Requires-Dist: pysam (>=0.8.4)
Provides-Extra: test
Requires-Dist: pytest-cov (>=2.5.1); extra == 'test'
